{
    "instance2index": {
        "_PAD_POS": 1,
        "_ROOT_POS": 2,
        "_END_POS": 3,
        "VV": 4,
        "ETM": 5,
        "NNG": 6,
        "JKS": 7,
        "NP": 8,
        "JKO": 9,
        "XSV": 10,
        "EC": 11,
        "MAG": 12,
        "XR": 13,
        "XSA": 14,
        "JKG": 15,
        "JKB": 16,
        "EP": 17,
        "EF": 18,
        "SF": 19,
        "JX": 20,
        "NNP": 21,
        "MM": 22,
        "ETN": 23,
        "NNB": 24,
        "VCN": 25,
        "SP": 26,
        "VA": 27,
        "VX": 28,
        "VCP": 29,
        "JC": 30,
        "XSN": 31,
        "XPN": 32,
        "SL": 33,
        "SN": 34,
        "MAJ": 35,
        "NR": 36,
        "JKC": 37,
        "SS": 38,
        "SH": 39,
        "SE": 40,
        "SW": 41,
        "Q": 42,
        "JKQ": 43,
        "IC": 44,
        "JKV": 45,
        "SO": 46,
        "NA": 47,
        "OBJ": 48,
        "MAC": 49,
        "MOD": 50,
        "NNH": 51
    },
    "instances": [
        "_PAD_POS",
        "_ROOT_POS",
        "_END_POS",
        "VV",
        "ETM",
        "NNG",
        "JKS",
        "NP",
        "JKO",
        "XSV",
        "EC",
        "MAG",
        "XR",
        "XSA",
        "JKG",
        "JKB",
        "EP",
        "EF",
        "SF",
        "JX",
        "NNP",
        "MM",
        "ETN",
        "NNB",
        "VCN",
        "SP",
        "VA",
        "VX",
        "VCP",
        "JC",
        "XSN",
        "XPN",
        "SL",
        "SN",
        "MAJ",
        "NR",
        "JKC",
        "SS",
        "SH",
        "SE",
        "SW",
        "Q",
        "JKQ",
        "IC",
        "JKV",
        "SO",
        "NA",
        "OBJ",
        "MAC",
        "MOD",
        "NNH"
    ],
    "singletions": []
}